stack_noodle/__init__.py
stack_noodle/eggnoodle.py
stack_noodle/friend_rice.py
stack_noodle-0.0.3.dist-info/LICENSE.txt
stack_noodle-0.0.3.dist-info/METADATA
stack_noodle-0.0.3.dist-info/WHEEL
stack_noodle-0.0.3.dist-info/top_level.txt
stack_noodle-0.0.3.dist-info/RECORD
