Metadata-Version: 2.1
Name: stack-noodle
Version: 0.0.3
Summary: Everyone love noodle
Home-page: UNKNOWN
Author: ['Isarafx', 'My lovely duck']
Author-email: isarawn@gmail.com
License: UNKNOWN
Platform: UNKNOWN
Classifier: Programming Language :: Python :: 3
Classifier: License :: OSI Approved :: MIT License
Classifier: Operating System :: OS Independent
Requires-Python: >=3
Requires-Dist: numpy
